{
  "cli": {
    "version": ">= 3.10.0",
    "appVersionSource": "remote"
  },
  "build": {
    "development": {
      "developmentClient": true,
      "distribution": "internal"
    },
    "preview": {
      "android": {
        "buildType": "apk"
      },
      "env": {
        "EXPO_PUBLIC_FIREBASE_API_KEY": "AIzaSyCkMN9eCxsS3j02Q_FdR41PC4M_ah9nJRE",
        "EXPO_PUBLIC_FIREBASE_AUTH_DOMAIN": "salah-times-744a5.firebaseapp.com",
        "EXPO_PUBLIC_FIREBASE_PROJECT_ID": "salah-times-744a5",
        "EXPO_PUBLIC_FIREBASE_STORAGE_BUCKET": "salah-times-744a5.firebasestorage.app",
        "EXPO_PUBLIC_FIREBASE_MESSAGING_SENDER_ID": "672675507739",
        "EXPO_PUBLIC_FIREBASE_APP_ID": "1:672675507739:web:f29e221aae07f3893452be",
        "EXPO_PUBLIC_FIREBASE_MEASUREMENT_ID": "G-MWJ5LNVPSW"
      }
    },
    "production": {
      "autoIncrement": true,
      "android": {
        "buildType": "app-bundle"
      }
    }
  },
  "submit": {
    "production": {}
  }
}